aio_modbus_client/BaseRegister.py
aio_modbus_client/BitsWrite.py
aio_modbus_client/CoilsRegister.py
aio_modbus_client/DataFormatter.py
aio_modbus_client/HoldingRegister.py
aio_modbus_client/InputRegister.py
aio_modbus_client/ModbusDevice.py
aio_modbus_client/ModbusDevice.schema.json
aio_modbus_client/ModbusDeviceMixin.py
aio_modbus_client/ModbusException.py
aio_modbus_client/ModbusProtocol.py
aio_modbus_client/ModbusProtocolEcho.py
aio_modbus_client/ModbusProtocolOcf.py
aio_modbus_client/ModbusProtocolRtu.py
aio_modbus_client/ModbusProtocolRtuHF5111.py
aio_modbus_client/ModbusProtocolTcp.py
aio_modbus_client/Transport.py
aio_modbus_client/TransportSerial.py
aio_modbus_client/TransportSocket.py
aio_modbus_client/TransportTest.py
aio_modbus_client/__init__.py
aio_modbus_client/utilites.py
aio_modbus_client-0.0.4.dist-info/LICENSE
aio_modbus_client-0.0.4.dist-info/METADATA
aio_modbus_client-0.0.4.dist-info/WHEEL
aio_modbus_client-0.0.4.dist-info/top_level.txt
aio_modbus_client-0.0.4.dist-info/RECORD
