Metadata-Version: 2.1
Name: aio-modbus-client
Version: 0.0.4
Summary: Easy work with modbus device. You do not need to know the protocol.
Home-page: https://github.com/businka/aio_modbus_client
Author: Mikhail Razgovorov
Author-email: 1338833@gmail.com
License: UNKNOWN
Platform: UNKNOWN
Classifier: Programming Language :: Python :: 3
Classifier: License :: OSI Approved :: Apache Software License
Classifier: Operating System :: OS Independent
Classifier: Framework :: AsyncIO
Requires-Python: >=3.5.3
Requires-Dist: serial-asyncio
